<?xml version="1.0" encoding="utf-8" ?>
<dwsync>
<file name="upload_apps.cfm" server="www.student-management.com//var/www/html/student-management/" local="129018251180000000" remote="129018251180000000" />
<file name="qr_page2.cfm" server="www.student-management.com//var/www/html/student-management/" local="129018287580000000" remote="129018287580000000" />
<file name="qr_page1.cfm" server="www.student-management.com//var/www/html/student-management/" local="129026042160000000" remote="129036378570000000" />
<file name="qr_page3.cfm" server="www.student-management.com//var/www/html/student-management/" local="128735704540000000" remote="128735704540000000" />
<file name="qr_page7.cfm" server="www.student-management.com//var/www/html/student-management/" local="128759999180000000" remote="128759999180000000" />
<file name="qr_interest.cfm" server="www.student-management.com//var/www/html/student-management/" local="128727050690000000" remote="128727050690000000" />
<file name="qr_page6.cfm" server="www.student-management.com//var/www/html/student-management/" local="128739129640000000" remote="128739129640000000" />
<file name="qr_page9.cfm" server="www.student-management.com//var/www/html/student-management/" local="128760004990000000" remote="128760004990000000" />
<file name="qr_medical_history4.cfm" server="www.student-management.com//var/www/html/student-management/" local="129036434190910963" remote="129036434230000000" />
<file name="upload_form.cfm" server="www.student-management.com//var/www/html/student-management/" local="128746016270000000" remote="128746016270000000" />
</dwsync>